Metadata-Version: 2.1
Name: pytest-iteration
Version: 0.1.0
Summary: Add iteration mark for tests
Home-page: https://github.com/hanzhichao/pytest-iteration
Author: Han Zhichao
Author-email: superhin@126.com
License: MIT license
Keywords: pytest,py.test,pytest-iteration,test iteration,pytest tester
Classifier: Framework :: Pytest
Classifier: Programming Language :: Python
Classifier: Topic :: Software Development :: Testing
Classifier: Programming Language :: Python :: 3.6
License-File: LICENSE
Requires-Dist: pytest
Requires-Dist: pytest-runner
